kaparoo_lightning/__about__.py
kaparoo_lightning/__init__.py
kaparoo_lightning/py.typed
kaparoo_lightning/common/__init__.py
kaparoo_lightning/common/spec.py
kaparoo_lightning/common/types.py
kaparoo_lightning/data/__init__.py
kaparoo_lightning/data/constants.py
kaparoo_lightning/data/dataloaders.py
kaparoo_lightning/data/datamodules.py
kaparoo_lightning/data/datasets.py
kaparoo_lightning/data/types.py
kaparoo_lightning/nn/__init__.py
kaparoo_lightning/nn/utils.py
kaparoo_lightning/nn/models/__init__.py
kaparoo_lightning/nn/models/gan.py
kaparoo_lightning/nn/modules/__init__.py
kaparoo_lightning/nn/modules/residuals.py
kaparoo_lightning/nn/specs/__init__.py
kaparoo_lightning/nn/specs/conv.py
kaparoo_lightning/nn/specs/module.py
kaparoo_lightning/nn/specs/norm.py
kaparoo_lightning-0.1.7.dist-info/METADATA
kaparoo_lightning-0.1.7.dist-info/WHEEL
kaparoo_lightning-0.1.7.dist-info/licenses/LICENSE
kaparoo_lightning-0.1.7.dist-info/RECORD
