Metadata-Version: 2.1
Name: kaparoo-lightning
Version: 0.1.7
Summary: A Python package for (personally) common and useful features for PyTorch Lightning.
Project-URL: GitHub, https://www.github.com/kaparoo/lightning-package
Author-email: Jaewoo Park <kaparoo2001@gmail.com>
License: MIT License
License-File: LICENSE
Keywords: pytorch lightning
Classifier: Development Status :: 4 - Beta
Classifier: Environment :: Console
Classifier: Environment :: GPU
Classifier: Environment :: GPU :: NVIDIA CUDA
Classifier: Intended Audience :: Developers
Classifier: Intended Audience :: Science/Research
Classifier: License :: OSI Approved :: MIT License
Classifier: Operating System :: OS Independent
Classifier: Programming Language :: Python
Classifier: Programming Language :: Python :: 3
Classifier: Programming Language :: Python :: 3 :: Only
Classifier: Programming Language :: Python :: 3.10
Classifier: Programming Language :: Python :: 3.11
Classifier: Programming Language :: Python :: Implementation :: CPython
Classifier: Topic :: Scientific/Engineering
Classifier: Topic :: Scientific/Engineering :: Artificial Intelligence
Classifier: Typing :: Typed
Requires-Python: >=3.10
Requires-Dist: kaparoo-python>=0.1.3
Requires-Dist: lightning>=2.0.6
Provides-Extra: dev
Requires-Dist: black>=23.7.0; extra == 'dev'
Requires-Dist: hatch>=1.7.0; extra == 'dev'
Requires-Dist: mypy>=1.4.1; extra == 'dev'
Requires-Dist: pytest>=7.4.0; extra == 'dev'
Requires-Dist: ruff>=0.0.282; extra == 'dev'
